tychos_skyfield/__init__.py
tychos_skyfield/baselib.py
tychos_skyfield/skyfieldlib.py
tychos_skyfield-1.0.8.dist-info/METADATA
tychos_skyfield-1.0.8.dist-info/WHEEL
tychos_skyfield-1.0.8.dist-info/licenses/LICENSE
tychos_skyfield-1.0.8.dist-info/RECORD
