Metadata-Version: 2.4
Name: tychos_skyfield
Version: 1.0.8
Summary: Package for Tychos model implementation in Python and Tychos model interface to the Skyfield package. https://github.com/mindaugl/tychos_skyfield
Project-URL: Homepage, https://github.com/mindaugl/tychos_skyfield
Project-URL: Issues, https://github.com/mindaugl/tychos_skyfield/issues
Author-email: Mindaugas Lekaveckas <mindelek@gmail.com>
License-Expression: GPL-2.0-only
License-File: LICENSE
Classifier: Operating System :: OS Independent
Classifier: Programming Language :: Python :: 3
Requires-Python: >=3.8
Requires-Dist: numpy
Requires-Dist: scipy
